sshping.py
sshping-0.1.4.data/scripts/sshping.py
sshping-0.1.4.dist-info/LICENSE
sshping-0.1.4.dist-info/METADATA
sshping-0.1.4.dist-info/WHEEL
sshping-0.1.4.dist-info/entry_points.txt
sshping-0.1.4.dist-info/top_level.txt
sshping-0.1.4.dist-info/RECORD
