Metadata-Version: 2.1
Name: sshping
Version: 0.1.4
Summary: ping utility that lets you ping hosts that are only defined in your ~/.ssh/config file
Home-page: https://github.com/buanzo/sshping
Author: Arturo "Buanzo" Busleiman
Author-email: buanzo@buanzo.com.ar
License: MIT License
Keywords: networking,ssh,ping
Classifier: Environment :: Console
Classifier: Intended Audience :: System Administrators
Classifier: Programming Language :: Python
Requires-Python: >=3.6
License-File: LICENSE
Requires-Dist: pythonping
Requires-Dist: sshconf
